dataclass_cli/__init__.py
dataclass_cli/parser.py
tests/__init__.py
tests/test_dc_cli.py
dc_cli-0.1.dist-info/LICENSE
dc_cli-0.1.dist-info/METADATA
dc_cli-0.1.dist-info/WHEEL
dc_cli-0.1.dist-info/top_level.txt
dc_cli-0.1.dist-info/RECORD
