Metadata-Version: 2.1
Name: dc-cli
Version: 0.1
Summary: Dataclass command line interface
Home-page: https://github.com/malte-soe/dataclass-cli
Author: Malte Soennichsen
Author-email: malte-soe@users.noreply.github.com
License: UNKNOWN
Platform: UNKNOWN
Classifier: Programming Language :: Python :: 3
Classifier: License :: OSI Approved :: MIT License
Classifier: Operating System :: OS Independent
Requires-Python: >=3.8
